msvcpp_normalize_pe/__init__.py
msvcpp_normalize_pe/__main__.py
msvcpp_normalize_pe/cli.py
msvcpp_normalize_pe/patcher.py
msvcpp_normalize_pe-0.0.post38.dist-info/licenses/LICENSE
msvcpp_normalize_pe-0.0.post38.dist-info/METADATA
msvcpp_normalize_pe-0.0.post38.dist-info/WHEEL
msvcpp_normalize_pe-0.0.post38.dist-info/entry_points.txt
msvcpp_normalize_pe-0.0.post38.dist-info/top_level.txt
msvcpp_normalize_pe-0.0.post38.dist-info/RECORD
