Metadata-Version: 2.4
Name: msvcpp-normalize-pe
Version: 0.0.post38
Summary: Normalize PE files for reproducible MSVC++ builds
Author-email: Tim Ansell <me@mith.ro>
License: Apache-2.0
Project-URL: Homepage, https://github.com/mithro/msvcpp-normalize-pe
Project-URL: Documentation, https://msvcpp-normalize-pe.readthedocs.io
Project-URL: Repository, https://github.com/mithro/msvcpp-normalize-pe
Project-URL: Issues, https://github.com/mithro/msvcpp-normalize-pe/issues
Project-URL: Changelog, https://github.com/mithro/msvcpp-normalize-pe/releases
Keywords: msvc,reproducible-builds,pe,windows,compiler,deterministic
Classifier: Development Status :: 4 - Beta
Classifier: Intended Audience :: Developers
Classifier: Topic :: Software Development :: Build Tools
Classifier: Topic :: Software Development :: Compilers
Classifier: License :: OSI Approved :: Apache Software License
Classifier: Operating System :: OS Independent
Classifier: Programming Language :: Python :: 3
Classifier: Programming Language :: Python :: 3.9
Classifier: Programming Language :: Python :: 3.10
Classifier: Programming Language :: Python :: 3.11
Classifier: Programming Language :: Python :: 3.12
Requires-Python: >=3.9
License-File: LICENSE
Dynamic: license-file
